IsPrime/IsPrime.py
IsPrime/__init__.py
cptsao-0.0.1.dist-info/LICENSE.txt
cptsao-0.0.1.dist-info/METADATA
cptsao-0.0.1.dist-info/WHEEL
cptsao-0.0.1.dist-info/top_level.txt
cptsao-0.0.1.dist-info/RECORD
