Metadata-Version: 2.1
Name: cptsao
Version: 0.0.1
Summary: example-pkg-Check_Prime_No.
Home-page: https://github.com/cptsao/PythonStudies.git
Author: C.P. Tsao
Author-email: cptsao@gmail.com
License: UNKNOWN
Platform: UNKNOWN
Classifier: Programming Language :: Python :: 3
Classifier: License :: OSI Approved :: MIT License
Classifier: Operating System :: OS Independent
Requires-Python: >=3.6
